google_analytics_data_json/__init__.py
google_analytics_data_json/create_ga4_request.py
google_analytics_data_json/google_analytics_data_json.py
google_analytics_data_json/transform_ga4_data.py
google_analytics_data_json-0.0.2.2.dist-info/LICENSE
google_analytics_data_json-0.0.2.2.dist-info/METADATA
google_analytics_data_json-0.0.2.2.dist-info/WHEEL
google_analytics_data_json-0.0.2.2.dist-info/top_level.txt
google_analytics_data_json-0.0.2.2.dist-info/RECORD
