Metadata-Version: 2.1
Name: google-analytics-data-json
Version: 0.0.2.2
Summary: A package to simplify fetching and transforming data from the Google Analytics Data GA4 API
Author-email: Daniel Jerrehian <danieljerrehian@gmail.com>
License: MIT License
Project-URL: Homepage, https://github.com/DanielJerrehian/google_analytics_data_json
Project-URL: Bug Tracker, https://github.com/DanielJerrehian/google_analytics_data_json/issues
Classifier: Programming Language :: Python :: 3
Classifier: License :: OSI Approved :: MIT License
Classifier: Operating System :: OS Independent
Requires-Python: >=3.7
License-File: LICENSE
Requires-Dist: cachetools <5.4,>=5.2.0
Requires-Dist: certifi ==2022.6.15
Requires-Dist: charset-normalizer ~=2.1.0
Requires-Dist: google-analytics-data ==0.12.1
Requires-Dist: google-api-core ==2.8.2
Requires-Dist: google-auth ==2.9.0
Requires-Dist: googleapis-common-protos ==1.56.3
Requires-Dist: grpcio ==1.47.0
Requires-Dist: grpcio-status ==1.47.0
Requires-Dist: idna <4,>=3.3
Requires-Dist: proto-plus ==1.20.6
Requires-Dist: protobuf ==3.20.1
Requires-Dist: pyasn1 ==0.4.8
Requires-Dist: pyasn1-modules ==0.2.8
Requires-Dist: python-dotenv ~=0.20.0
Requires-Dist: requests >=2.28.1
Requires-Dist: rsa ~=4.8
Requires-Dist: six ~=1.16.0
Requires-Dist: google-api-python-client ~=2.86.0
